pygushi/__init__.py
pygushi/__main__.py
pygushi/author.py
pygushi/datas.py
pygushi/login.py
pygushi/poetry.py
pygushi/version.py
pygushi-1.2.0.dist-info/LICENSE
pygushi-1.2.0.dist-info/METADATA
pygushi-1.2.0.dist-info/WHEEL
pygushi-1.2.0.dist-info/top_level.txt
pygushi-1.2.0.dist-info/RECORD
