Metadata-Version: 2.1
Name: pygushi
Version: 1.2.0
Summary: 一个关于爬取古诗文的Python3 API
Home-page: https://github.com/stripepython/pygushi
Download-URL: https://github.com/stripepython/pygushi
Author: stripe-python
Author-email: stripe-python@139.com
Maintainer: stripe-python
Maintainer-email: stripe-python@139.com
License: Apache License
Requires-Python: >=3.7
License-File: LICENSE
Requires-Dist: requests (~=2.28.1)
Requires-Dist: ddddocr (<=1.1.0)
Requires-Dist: retry (~=0.9.2)
Requires-Dist: beautifulsoup4 (~=4.11.1)
Requires-Dist: pillow (~=9.3.0)
Requires-Dist: click (~=8.1.3)
